{
  "checked_at": "2026-01-09T10:12:32.429570383Z",
  "network_health": {
    "total_relays": 5,
    "healthy": 5,
    "degraded": 0,
    "offline": 0,
    "score": 1
  },
  "relays": [
    {
      "name": "relayer1",
      "address": "80.78.27.15:9001",
      "roles": [
        "entry",
        "middle",
        "exit"
      ],
      "status": "healthy",
      "checks": {
        "metrics": {
          "status": "ok",
          "latency_ms": 332,
          "version": "go1.25.5 X:nodwarf5",
          "circuits_active": 80,
          "bytes_received": 612820,
          "bytes_sent": 25052
        },
        "circuit": {
          "status": "ok",
          "latency_ms": 764,
          "circuit_id": "3d05a375"
        },
        "http": {
          "status": "ok",
          "latency_ms": 454,
          "status_code": 200,
          "test_site": "tonnet-sync-check.ton"
        }
      }
    },
    {
      "name": "relayer2",
      "address": "80.78.25.121:9001",
      "roles": [
        "entry",
        "middle",
        "exit"
      ],
      "status": "healthy",
      "checks": {
        "metrics": {
          "status": "ok",
          "latency_ms": 304,
          "version": "go1.25.5 X:nodwarf5",
          "circuits_active": 33,
          "bytes_received": 253292,
          "bytes_sent": 9940
        },
        "circuit": {
          "status": "ok",
          "latency_ms": 710,
          "circuit_id": "dcf35642"
        },
        "http": {
          "status": "ok",
          "latency_ms": 393,
          "status_code": 200,
          "test_site": "tonnet-sync-check.ton"
        }
      }
    },
    {
      "name": "relayer3",
      "address": "80.78.27.23:9001",
      "roles": [
        "entry",
        "middle",
        "exit"
      ],
      "status": "healthy",
      "checks": {
        "metrics": {
          "status": "ok",
          "latency_ms": 336,
          "version": "go1.25.5 X:nodwarf5",
          "circuits_active": 48,
          "bytes_received": 156352,
          "bytes_sent": 4160
        },
        "circuit": {
          "status": "ok",
          "latency_ms": 735,
          "circuit_id": "510680d9"
        },
        "http": {
          "status": "ok",
          "latency_ms": 402,
          "status_code": 200,
          "test_site": "tonnet-sync-check.ton"
        }
      }
    },
    {
      "name": "relayer4",
      "address": "80.78.25.177:9001",
      "roles": [
        "entry",
        "middle",
        "exit"
      ],
      "status": "healthy",
      "checks": {
        "metrics": {
          "status": "ok",
          "latency_ms": 317,
          "version": "go1.25.5 X:nodwarf5",
          "circuits_active": 67,
          "bytes_received": 163040,
          "bytes_sent": 4392
        },
        "circuit": {
          "status": "ok",
          "latency_ms": 740,
          "circuit_id": "6762ae1d"
        },
        "http": {
          "status": "ok",
          "latency_ms": 431,
          "status_code": 200,
          "test_site": "tonnet-sync-check.ton"
        }
      }
    },
    {
      "name": "relayer5",
      "address": "46.62.171.242:9001",
      "roles": [
        "entry",
        "middle"
      ],
      "status": "healthy",
      "checks": {
        "metrics": {
          "status": "ok",
          "latency_ms": 357,
          "version": "go1.25.5 X:nodwarf5",
          "circuits_active": 301,
          "bytes_received": 4,
          "bytes_sent": 415284
        },
        "circuit": {
          "status": "ok",
          "latency_ms": 801,
          "circuit_id": "1594580d"
        },
        "http": {
          "status": "ok",
          "latency_ms": 502,
          "status_code": 200,
          "test_site": "tonnet-sync-check.ton"
        }
      }
    }
  ]
}
